Metadata-Version: 2.1
Name: switchpy
Version: 0.0.2
Summary: A simple python switch case library
Home-page: https://github.com/pranavbaburaj/python-switch
Author: P Pranav Baburaj
License: UNKNOWN
Platform: UNKNOWN
Classifier: Programming Language :: Python :: 3
Classifier: License :: OSI Approved :: MIT License
Classifier: Operating System :: OS Independent
Requires-Python: >=3.6
